{
  "timestamp": "2026-05-08T06:03:45.580414",
  "account": "dreamdemo",
  "check_type": "exit_skill_v2",
  "dry_run": false,
  "has_position": true,
  "position": {
    "adl": "1",
    "availPos": "0.01",
    "avgPx": "79763.5",
    "baseBal": "",
    "baseBorrowed": "",
    "baseInterest": "",
    "bePx": "79843.30340170085",
    "bizRefId": "",
    "bizRefType": "",
    "cTime": "1778190895423",
    "ccy": "USDT",
    "clSpotInUseAmt": "",
    "closeAllFlag": "0",
    "closeOrderAlgo": [],
    "deltaBS": "",
    "deltaPA": "",
    "estMaxWin": "",
    "fee": "-0.003988175",
    "fundingFee": "0",
    "gammaBS": "",
    "gammaPA": "",
    "hedgedPos": "",
    "idxPx": "79710.3",
    "imr": "",
    "instId": "BTC-USDT-SWAP",
    "instType": "SWAP",
    "interest": "",
    "last": "79677.9",
    "lever": "2",
    "liab": "",
    "liabCcy": "",
    "liqPenalty": "0",
    "liqPx": "40062.1291310899",
    "margin": "3.988175",
    "markPx": "79667.2",
    "maxSpotInUseAmt": "",
    "mgnMode": "isolated",
    "mgnRatio": "110.97680238681802",
    "mmr": "0.03186688",
    "nonSettleAvgPx": "",
    "notionalUsd": "7.965285990400001",
    "optVal": "",
    "pendingCloseOrdLiabVal": "",
    "pnl": "0",
    "pos": "0.01",
    "posCcy": "",
    "posId": "3523356312296591360",
    "posSide": "long",
    "quoteBal": "",
    "quoteBorrowed": "",
    "quoteInterest": "",
    "realizedPnl": "-0.003988175",
    "settledPnl": "",
    "spotInUseAmt": "",
    "spotInUseCcy": "",
    "thetaBS": "",
    "thetaPA": "",
    "tradeId": "3351648424",
    "uTime": "1778190895423",
    "upl": "-0.0096300000000003",
    "uplLastPx": "-0.0085600000000006",
    "uplRatio": "-0.0024146382743988",
    "uplRatioLastPx": "-0.002146345132799",
    "usdPx": "0.99982",
    "vegaBS": "",
    "vegaPA": ""
  },
  "market_features": {
    "current_price": 79678.5,
    "avg_price": 79763.5,
    "unrealized_pct": -0.11,
    "funding_rate": 3.36618633795e-05,
    "volatility_percentile": 42.0,
    "volume_ratio": 0.52,
    "momentum_divergence": true,
    "correlation_surge": -1.0
  },
  "exit_skill_result": {
    "action": "hold",
    "risk_level": "low",
    "risk_sources": [],
    "should_escalate": false,
    "recommendations": []
  },
  "final_decision": "HOLD",
  "decision_reason": "L2: \u98ce\u9669\u53ef\u63a5\u53d7",
  "action_taken": null,
  "execution_result": null,
  "errors": [],
  "market_regime": "trending",
  "trend_indicators": {
    "ma_consensus": 0.5,
    "adx": 29.6
  }
}